{"10000_Name":"自然界的恩賜","10000_Text":"使用特殊方塊時，根據回復力回復生命值。[5ef5f7] ( 可重複 ) [-]","10001_Name":"回復之舞","10001_Text":"使用特殊方塊時，回復[5ef5f7]15,000[-]點生命值。[5ef5f7] ( 可重複 ) [-]","10002_Name":"魂之舞","10002_Text":"使用特殊方塊時，增加[5ef5f7]1[-]魂。[5ef5f7] ( 可重複 ) [-]","10003_Name":"魂之誓","10003_Text":"使用特殊方塊時，增加[5ef5f7]2[-]魂。[5ef5f7] ( 可重複 ) [-]","10004_Name":"追擊之陣","10004_Text":"使用特殊方塊攻擊時，發動追擊。","10005_Name":"亞人的威嚇","10005_Text":"使用特殊方塊時，降低敵人防禦力。[5ef5f7] ( 可重複 ) [-]","10010_Name":"生命之禱告","10010_Text":"使用特殊方塊時，回復生命值，並增加[5ef5f7]１[-]魂。[5ef5f7] ( 可重複 ) [-]","10011_Name":"武士之魂","10011_Text":"使用特殊方塊時，回復生命值，並增加[5ef5f7]１[-]魂。[5ef5f7] ( 可重複 ) [-]","10012_Name":"天界之魂","10012_Text":"使用特殊方塊時，回復生命值，並增加[5ef5f7]１[-]魂。[5ef5f7] ( 可重複 ) [-]","10013_Name":"最古之魂","10013_Text":"使用特殊方塊時，回復生命值，並增加[5ef5f7]１[-]魂。[5ef5f7] ( 可重複 ) [-]","10014_Name":"英雄之魂","10014_Text":"使用特殊方塊時，回復生命值，並增加[5ef5f7]１[-]魂。[5ef5f7] ( 可重複 ) [-]","10015_Name":"英雄王之魂","10015_Text":"使用特殊方塊時，回復生命值，並增加[5ef5f7]１[-]魂。[5ef5f7] ( 可重複 ) [-]","10020_Name":"修練式","10020_Text":"使用特殊方塊時，提升一點隊伍攻擊力。 ( 重複無效 ) ","10021_Name":"修練式．改","10021_Text":"使用特殊方塊時，大幅提升隊伍攻擊力。 ( 重複無效 ) ","10022_Name":"修煉之舞","10022_Text":"使用特殊方塊時，提升隊伍攻擊力。 ( 重複無效 ) ","10030_Name":"重力結界","10030_Text":"消除2枚以上特殊方塊時，敵人行動延遲[5ef5f7]2[-]回合。 ( 重複無效 ) ","10031_Name":"重力結界．改","10031_Text":"消除2枚以上特殊方塊時，敵人行動延遲[5ef5f7]3[-]回合。 ( 重複無效 ) ","10040_Name":"回復之陣","10040_Text":"使用特殊方塊時，回復[5ef5f7]15,000[-]點生命值。[5ef5f7] ( 可重複 ) [-]","10041_Name":"治癒之炎","10041_Text":"使用特殊方塊時，回復[5ef5f7]20,000[-]點生命值。[5ef5f7] ( 可重複 ) [-]","10042_Name":"發迷","10042_Text":"使用特殊方塊時，回復[5ef5f7]20,000[-]點生命值。[5ef5f7] ( 可重複 ) [-]","10100_Name":"迷曲","10100_Text":"使用特殊方塊時，重新抽選所有方塊。","10110_Name":"四屬之舞","10110_Text":"使用特殊方塊時，增加[5ef5f7]1[-]點屬性加乘。[5ef5f7] ( 可重複 ) [-]","10111_Name":"四屬之舞．改","10111_Text":"使用特殊方塊時，增加[5ef5f7]2[-]點屬性加乘。[5ef5f7] ( 可重複 ) [-]","10120_Name":"魂之召喚","10120_Text":"消除2枚以上特殊方塊時，增加[5ef5f7]6[-]魂。 ( 重複無效 ) ","10200_Name":"一閃","10200_Text":"使用特殊方塊時，對敵人造成[5ef5f7]50,000[-]點傷害。[5ef5f7] ( 可重複 ) [-]","10210_Name":"詛咒攻擊","10210_Text":"消除2枚以上特殊方塊時，令敵人陷入詛咒狀態。 ( 重複無效 ) ","10220_Name":"吸收攻擊","10220_Text":"使用特殊方塊攻擊時，根據傷害回復生命值。 ( 重複無效 ) ","10300_Name":"界限突破","10300_Text":"使用特殊方塊後，[5ef5f7]3[-]回合以內攻擊力[5ef5f7]超絕[-]提升。 ( 重複無效 ) ","10301_Name":"全身全靈","10301_Text":"使用特殊方塊後，[5ef5f7]3[-]回合以內全力一擊發生率[5ef5f7]超絕[-]提升。 ( 重複無效 ) ","10400_Name":"魂之選定","10400_Text":"使用特殊方塊時，移動時增加魂，戰鬥時回復生命值。[5ef5f7] ( 可重複 ) [-]","10410_Name":"極意潛行","10410_Text":"使用特殊方塊移動時，不會遇敵。","10420_Name":"回復之滴","10420_Text":"使用特殊方塊後，[5ef5f7]3[-]回合以內使用方塊時回復生命值。 ( 重複無效 ) ","10430_Name":"鋼鐵意志","10430_Text":"使用特殊方塊後，[5ef5f7]3[-]回合以內使用方塊時回復生命值。 ( 重複無效 ) ","10500_Name":"吸收生命","10500_Text":"使用特殊方塊時，最大生命值上升。(重複無效，設有上限)","10510_Name":"饋贈","10510_Text":"使用特殊方塊時，隨機發動回復生命值、增加魂、強化屬性之一。","10520_Name":"誘惑","10520_Text":"使用特殊方塊時，隨機發動回復生命值、增加魂、強化屬性之一。","10600_Name":"點穴","10600_Text":"使用特殊方塊時，對敵人造成[5ef5f7]10,000[-]點傷害，並降低其防禦力。[5ef5f7] ( 可重複 ) [-]","10650_Name":"神聖審判","10650_Text":"使用特殊方塊時，根據隊員的回復力，對敵人造成傷害。 ( 重複無效 ) ","10700_Name":"絕對防禦","10700_Text":"每消除1枚特殊方塊，減輕[5ef5f7]35%[-]來自敵人的下一攻擊。 ( 重複無效 ) ","10701_Name":"龍鐵裝","10701_Text":"每消除1枚特殊方塊，減輕[5ef5f7]20%[-]來自敵人的下一攻擊。 ( 重複無效 ) ","10800_Name":"爆炎之舞","10800_Text":"使用特殊方塊後，[5ef5f7]5[-]回合以內火屬性戰士攻擊力提升。[5ef5f7] ( 可重複 ) [-]","10810_Name":"激流之舞","10810_Text":"使用特殊方塊後，[5ef5f7]5[-]回合以內水屬性戰士攻擊力提升。[5ef5f7] ( 可重複 ) [-]","10900_Name":"特殊漿液","10900_Text":"使用2枚特殊方塊攻擊時，提升隊伍攻擊力，無視敵人防禦力。 ( 重複無效 ) ","10901_Name":"蜂蜜","10901_Text":"使用特殊方塊時，回復[5ef5f7]8,888[-]點生命值。[5ef5f7] ( 可重複 ) [-]","10902_Name":"終極一刻","10902_Text":"使用2枚特殊方塊時，停止[5ef5f7]5秒[-]時間，期間同時使用2枚相同的職業方塊，可造成追加傷害。","10903_Name":"絕招","10903_Text":"使用特殊方塊時，對敵人造成傷害；同時使用2枚時，所有方塊變為杖方塊。","11000_Name":"祝福","11000_Text":"使用特殊方塊時，魂增加[5ef5f7]1[-]；同時使用2枚時，生命值[5ef5f7]全回復[-]。","11020_Name":"常暗之術","11020_Text":"使用特殊方塊後，[5ef5f7]5[-]回合以內暗屬性戰士的攻擊力增加。[5ef5f7] ( 可重複 ) [-]","11030_Name":"最古之秘法","11030_Text":"使用特殊方塊時，對敵人造成傷害；同時使用2枚時，所有方塊變為弓方塊。","11040_Name":"激情之舞","11040_Text":"使用特殊方塊後，[5ef5f7]5[-]回合以內火屬性戰士的攻擊力增加。[5ef5f7] ( 可重複 ) [-]","11050_Name":"變異","11050_Text":"使用特殊方塊時，隨機發動回復生命值、增加魂、強化屬性之一。","11060_Name":"劍魂一敵","11060_Text":"使用特殊方塊時，將上列4枚方塊轉成[5ef5f7]劍[-]方塊。","11100_Name":"人槍合一","11100_Text":"使用特殊方塊時，將上列4枚方塊轉成[5ef5f7]槍[-]方塊。","11200_Name":"歌姬詠唱","11200_Text":"使用特殊方塊時，將上列4枚方塊轉成[5ef5f7]杖[-]方塊。","11500_Name":"父性覺醒","11500_Text":"使用特殊方塊時，根據回復力回復生命值。[5ef5f7] ( 可重複 ) [-]","11650_Name":"鍵守族之計","11650_Text":"只有使用特殊方塊攻擊時，隊伍攻擊力增加消耗方塊數目×[5ef5f7]1500[-]。(不可重複)","11700_Name":"治癒之光","11700_Text":"使用特殊方塊時，隊伍生命值回復消耗數目×[5ef5f7]5,000[-]。(不可重複)","11800_Name":"真實之劍","11800_Text":"使用特殊方塊時，對敵人造成傷害；同時使用2枚時，所有方塊變為[5ef5f7]劍[-]方塊。","11850_Name":"小丑之極致","11850_Text":"使用特殊方塊時，隨機發動回復生命值、增加魂、強化屬性之一。","11900_Name":"導引之魔力","11900_Text":"使用特殊方塊時，增加[5ef5f7]2[-]點屬性加乘。[5ef5f7](可重複)[-]","11950_Name":"抵抗之影","11950_Text":"使用特殊方塊時，回復生命值，並增加[5ef5f7]１[-]魂。[5ef5f7](可重複)[-]","12000_Name":"鈍色之魔王","12000_Text":"使用特殊方塊時，增加[5ef5f7]1[-]點屬性加乘。[5ef5f7](可重複)[-]"}